labs/lab08/top.sv
`default_nettype none
// Empty top module

module top (
  // I/O ports
  input  logic hz100, reset,
  input  logic [20:0] pb,
  output logic [7:0] left, right,
         ss7, ss6, ss5, ss4, ss3, ss2, ss1, ss0,
  output logic red, green, blue,

  // UART ports
  output logic [7:0] txdata,
  input  logic [7:0] rxdata,
  output logic txclk, rxclk,
  input  logic txready, rxready
);

  // Your code goes here...
  wire [3:0] buttons;
  wire en_wire;
  
  prienc16to4 penc (.in(pb[15:0]), .out(buttons), .strobe(en_wire));
  
  ssdec sd (.in(buttons), .enable(en_wire), .out(ss0[6:0]));
  
endmodule

// Add more modules down here...
module ssdec (
  input logic [3:0] in,
  input logic enable,
  output logic [6:0] out
);
  assign out = (enable == 1'b1)? 
               (in == 4'b0000)? 7'b0111111 :
               (in == 4'b0001)? 7'b0000110 :
               (in == 4'b0010)? 7'b1011011 :
               (in == 4'b0011)? 7'b1001111 :
               (in == 4'b0100)? 7'b1100110 :
               (in == 4'b0101)? 7'b1101101 :
               (in == 4'b0110)? 7'b1111101 :
               (in == 4'b0111)? 7'b0000111 :
               (in == 4'b1000)? 7'b1111111 :
               (in == 4'b1001)? 7'b1100111 :
               (in == 4'b1010)? 7'b1110111 :
               (in == 4'b1011)? 7'b1111100 :
               (in == 4'b1100)? 7'b0111001 :
               (in == 4'b1101)? 7'b1011110 :
               (in == 4'b1110)? 7'b1111001 :
               7'b1110001 : 7'b0000000;
endmodule

module prienc16to4 (
    input logic [15:0] in,
    output logic [3:0] out,
    output logic strobe
);

    assign {out, strobe} = (in[15] == 1)? 5'b11111 :
                           (in[14] == 1)? 5'b11101 :
                           (in[13] == 1)? 5'b11011 :
                           (in[12] == 1)? 5'b11001 :
                           (in[11] == 1)? 5'b10111 :
                           (in[10] == 1)? 5'b10101 :
                           (in[9] == 1)? 5'b10011 :
                           (in[8] == 1)? 5'b10001 :
                           (in[7] == 1)? 5'b01111 :
                           (in[6] == 1)? 5'b01101 :
                           (in[5] == 1)? 5'b01011 :
                           (in[4] == 1)? 5'b01001 :
                           (in[3] == 1)? 5'b00111 :
                           (in[2] == 1)? 5'b00101 :
                           (in[1] == 1)? 5'b00011 :
                           (in[0] == 1)? 5'b00001 :
                           5'b00000;

endmodule

labs/lab08/tb.sv
////////////////////////////////////////////////////////////////////// 
// YOU SHOULD NOT BE LOOKING AT OR EDITING ANYTHING IN THIS FILE.
// AN ATTEMPT TO DO SO WILL BE CONSIDERED ACADEMIC DISHONESTY.
//////////////////////////////////////////////////////////////////////

module lab_testbench ();

logic [4:0] in;
logic enable;
logic [6:0] out;

ssdec sd (.in(in[3:0]), .enable(enable), .out(out));

integer STDERR = 32'h8000_0002;
logic errored;

logic [6:0] segment [15:0];
assign {segment[4'hF], segment[4'hE], segment[4'hD], segment[4'hC], 
        segment[4'hB], segment[4'hA], segment[4'h9], segment[4'h8], 
        segment[4'h7], segment[4'h6], segment[4'h5], segment[4'h4], 
        segment[4'h3], segment[4'h2], segment[4'h1], segment[4'h0]
        } = 112'hE3E6F39F9DF3FF0FF76E69F6C33F;

logic [7:0] ans;
logic [1023:0] testname;

initial begin
    $dumpfile ("lab08.vcd");
    $dumpvars (0, lab_testbench);
    errored = 0;
    // put tests here
    testname = "ssdec Enable Tests";
    enable = 0;
    in = 0;
    #10;
    for (in = 0; in < 16; in += 1) begin
        #10;
        if (out != 0) begin
            $fdisplay(STDERR,"ERROR: Expected ssdec out = 0 when enable = 0, in = %d", in);
            errored += 1;
        end
    end
    if (errored == 16) begin
        $fdisplay(STDERR,"ERROR: Your ssdec 'out' should be 0 whenever the enable is off.");
    end

    testname = "ssdec Output Tests";
    in = 0;
    enable = 1;
    #10;
    for (in = 0; in < 16; in += 1) begin
        #10;
        ans = segment[in];
        if (out != ans) begin
            $fdisplay(STDERR,"ERROR: Expected out = 7'b%b, but got 7'b%b, when in = 4'd%d", ans, out, in);
            errored = 1;
        end
    end
    if (errored == 0)
        $finish;
    else
        $stop;
end

endmodule

labs/lab08/lab08.vcd
$date
	Fri Mar 25 07:37:51 2022
$end
$version
	Icarus Verilog
$end
$timescale
	1s
$end
$scope module lab_testbench $end
$var wire 7 ! out [6:0] $end
$var reg 8 " ans [7:0] $end
$var reg 1 # enable $end
$var reg 1 $ errored $end
$var reg 5 % in [4:0] $end
$var reg 1024 & testname [1023:0] $end
$var integer 32 ' STDERR [31:0] $end
$scope module sd $end
$var wire 1 # enable $end
$var wire 4 ( in [3:0] $end
$var wire 7 ) out [6:0] $end
$upscope $end
$upscope $end
$enddefinitions $end
#0
$dumpvars
b0 )
b0 (
b10000000000000000000000000000010 '
b11100110111001101100100011001010110001100100000010001010110111001100001011000100110110001100101001000000101010001100101011100110111010001110011 &
b0 %
0$
0#
bx "
b0 !
$end
#20
b1 (
b1 %
#30
b10 (
b10 %
#40
b11 (
b11 %
#50
b100 (
b100 %
#60
b101 (
b101 %
#70
b110 (
b110 %
#80
b111 (
b111 %
#90
b1000 (
b1000 %
#100
b1001 (
b1001 %
#110
b1010 (
b1010 %
#120
b1011 (
b1011 %
#130
b1100 (
b1100 %
#140
b1101 (
b1101 %
#150
b1110 (
b1110 %
#160
b1111 (
b1111 %
#170
b111111 !
b111111 )
b0 (
1#
b11100110111001101100100011001010110001100100000010011110111010101110100011100000111010101110100001000000101010001100101011100110111010001110011 &
b0 %
#190
b110 !
b110 )
b1 (
b1 %
b111111 "
#200
b1011011 !
b1011011 )
b10 (
b10 %
b110 "
#210
b1001111 !
b1001111 )
b11 (
b11 %
b1011011 "
#220
b1100110 !
b1100110 )
b100 (
b100 %
b1001111 "
#230
b1101101 !
b1101101 )
b101 (
b101 %
b1100110 "
#240
b1111101 !
b1111101 )
b110 (
b110 %
b1101101 "
#250
b111 !
b111 )
b111 (
b111 %
b1111101 "
#260
b1111111 !
b1111111 )
b1000 (
b1000 %
b111 "
#270
b1100111 !
b1100111 )
b1001 (
b1001 %
b1111111 "
#280
b1110111 !
b1110111 )
b1010 (
b1010 %
b1100111 "
#290
b1111100 !
b1111100 )
b1011 (
b1011 %
b1110111 "
#300
b111001 !
b111001 )
b1100 (
b1100 %
b1111100 "
#310
b1011110 !
b1011110 )
b1101 (
b1101 %
b111001 "
#320
b1111001 !
b1111001 )
b1110 (
b1110 %
b1011110 "
#330
b1110001 !
b1110001 )
b1111 (
b1111 %
b1111001 "
#340
b111111 !
b111111 )
b0 (
b10000 %
b1110001 "
